lusidfeature/__init__.py
lusidfeature/feature_extractor.py
lusidfeature/feature_file_writer.py
lusidfeature/features_temp_file_manager.py
lusidfeature/get_project_root.py
lusidfeature/lusid_feature.py
lusidfeature/main.py
lusidfeature/reporter.py
lusidfeature-0.2.4.dist-info/LICENSE.md
lusidfeature-0.2.4.dist-info/METADATA
lusidfeature-0.2.4.dist-info/WHEEL
lusidfeature-0.2.4.dist-info/top_level.txt
lusidfeature-0.2.4.dist-info/RECORD
