Metadata-Version: 2.1
Name: lusidfeature
Version: 0.2.4
Summary: This package will allow to run the main file and retrieve a list of decorated feature methods in a cls
Home-page: https://github.com/finbourne/lusid-features-python.git
Author: FINBOURNE Technology
Author-email: engineering@finbourne.com
License: MIT
Keywords: OpenAPI,FINBOURNE,LUSID,LUSID API
Platform: UNKNOWN
Classifier: Programming Language :: Python :: 3
Classifier: License :: OSI Approved :: MIT License
Classifier: Operating System :: OS Independent
Requires-Python: >=3.6
Requires-Dist: parameterized (>=0.7.4)
